mptcplib/__init__.py
mptcplib/__init__.pyi
mptcplib/_common_constants.py
mptcplib/_interface.py
mptcplib/_mptcplib_linux.py
mptcplib/test/__init__.py
mptcplib/test/test_io.py
mptcplib/test/test_socket.py
mptcplib-0.1.3.dist-info/METADATA
mptcplib-0.1.3.dist-info/WHEEL
mptcplib-0.1.3.dist-info/licenses/LICENSE
mptcplib-0.1.3.dist-info/RECORD
