Metadata-Version: 2.1
Name: mptcplib
Version: 0.1.3
Summary: A Multipath TCP python support library
Project-URL: Homepage, https://github.com/mptcp-apps/mptcplib
Author-email: Ingenzi Vany <ingenzivany@gmail.com>
License-File: LICENSE
Classifier: Development Status :: 1 - Planning
Classifier: License :: OSI Approved :: MIT License
Classifier: Operating System :: POSIX
Classifier: Operating System :: POSIX :: Linux
Classifier: Operating System :: Unix
Classifier: Programming Language :: Python
Classifier: Programming Language :: Python :: 3 :: Only
Classifier: Topic :: System :: Networking
Classifier: Topic :: System :: Operating System Kernels :: Linux
Classifier: Typing :: Typed
Requires-Python: >=3.7
